zih_models/__init__.py
zih_models/py.typed
zih_models/sharepoint_backend/__init__.py
zih_models/sharepoint_backend/models.py
zih_models/tkdb/__init__.py
zih_models/tkdb/api_models.py
zih_models/tkdb/history_models/__init__.py
zih_models/tkdb/history_models/base.py
zih_models/tkdb/history_models/external_number.py
zih_models/tkdb/history_models/functional_number.py
zih_models/tkdb/history_models/mapping.py
zih_models/tkdb/history_models/personal_number.py
zih_models/tkdb/history_models/telephone_number.py
zih_models/tkdb/history_models/user.py
zih_models/tkdb/types.py
zih_models-0.4.3.dist-info/LICENSE
zih_models-0.4.3.dist-info/METADATA
zih_models-0.4.3.dist-info/WHEEL
zih_models-0.4.3.dist-info/RECORD
