Metadata-Version: 2.3
Name: zih-models
Version: 0.4.3
Summary: Pydantic models for ZIH services
License: MIT
Author: Ansgar Burchardt
Author-email: ansgar.burchardt@tu-dresden.de
Requires-Python: >=3.13
Classifier: Programming Language :: Python :: 3
Classifier: Operating System :: OS Independent
Requires-Dist: pydantic (>=2.11.7,<3.0.0)
Project-URL: Repository, https://gitlab.hrz.tu-chemnitz.de/zih/sde/zih-models
